kpi_monitor/__init__.py
kpi_monitor/dashboard.py
kpi_monitor/data_analysis.py
kpi_monitor/data_clean.py
kpi_monitor/data_get.py
kpi_monitor/utils.py
kpi_monitor-1.1.0.dist-info/METADATA
kpi_monitor-1.1.0.dist-info/WHEEL
kpi_monitor-1.1.0.dist-info/entry_points.txt
kpi_monitor-1.1.0.dist-info/RECORD
