Metadata-Version: 2.1
Name: kpi_monitor
Version: 1.1.0
Summary: 
Author: trading
Author-email: trading@flowertech.se
Requires-Python: >=3.11,<4.0
Classifier: Programming Language :: Python :: 3
Classifier: Programming Language :: Python :: 3.11
Classifier: Programming Language :: Python :: 3.12
Classifier: Programming Language :: Python :: 3.13
Requires-Dist: jupyter (>=1.1.1,<2.0.0)
Requires-Dist: matplotlib (>=3.9.2,<4.0.0)
Requires-Dist: pandas (>=2.0.2,<3.0.0)
Requires-Dist: psycopg2-binary (>=2.9.10,<3.0.0)
Requires-Dist: pydantic (>=1.10.7,<2.0.0)
Requires-Dist: pymysql (>=1.1.1,<2.0.0)
Requires-Dist: python-dotenv (>=1.0.1,<2.0.0)
Requires-Dist: streamlit (>=1.40.1,<2.0.0)
